package_auto_assembler/__init__.py
package_auto_assembler/cli.py
package_auto_assembler/package_auto_assembler.py
package_auto_assembler/setup.py
package_auto_assembler/.paa.tracking/.drawio
package_auto_assembler/.paa.tracking/.paa.config
package_auto_assembler/.paa.tracking/.paa.version
package_auto_assembler/.paa.tracking/lsts_package_versions.yml
package_auto_assembler/.paa.tracking/notebook.ipynb
package_auto_assembler/.paa.tracking/package_licenses.json
package_auto_assembler/.paa.tracking/package_mapping.json
package_auto_assembler/.paa.tracking/release_notes.md
package_auto_assembler/.paa.tracking/version_logs.csv
package_auto_assembler/.paa.tracking/extra_docs/cli_tools.md
package_auto_assembler/.paa.tracking/extra_docs/code_management.md
package_auto_assembler/.paa.tracking/extra_docs/python_packaging_repo.md
package_auto_assembler/.paa.tracking/python_modules/package_auto_assembler.py
package_auto_assembler/.paa.tracking/python_modules/components/paa_deps/artifacts_handler.py
package_auto_assembler/.paa.tracking/python_modules/components/paa_deps/cli_handler.py
package_auto_assembler/.paa.tracking/python_modules/components/paa_deps/dependencies_analyzer.py
package_auto_assembler/.paa.tracking/python_modules/components/paa_deps/drawio_handler.py
package_auto_assembler/.paa.tracking/python_modules/components/paa_deps/fastapi_handler.py
package_auto_assembler/.paa.tracking/python_modules/components/paa_deps/import_mapping_handler.py
package_auto_assembler/.paa.tracking/python_modules/components/paa_deps/local_dependencies_handler.py
package_auto_assembler/.paa.tracking/python_modules/components/paa_deps/long_doc_handler.py
package_auto_assembler/.paa.tracking/python_modules/components/paa_deps/metadata_handler.py
package_auto_assembler/.paa.tracking/python_modules/components/paa_deps/mkdocs_handler.py
package_auto_assembler/.paa.tracking/python_modules/components/paa_deps/ppr_handler.py
package_auto_assembler-0.5.29.dist-info/licenses/LICENSE
package_auto_assembler-0.5.29.dist-info/METADATA
package_auto_assembler-0.5.29.dist-info/WHEEL
package_auto_assembler-0.5.29.dist-info/entry_points.txt
package_auto_assembler-0.5.29.dist-info/top_level.txt
package_auto_assembler-0.5.29.dist-info/RECORD
