Metadata-Version: 2.4
Name: package_auto_assembler
Version: 0.5.29
Summary: A tool to automate package creation within ci based on just .py and optionally .ipynb file.
Home-page: https://kiril-mordan.github.io/reusables/package_auto_assembler/
Author: Kyrylo Mordan
Author-email: parachute.repo@gmail.com
License: mit
Keywords: python,packaging,aa-paa-tool
Classifier: Intended Audience :: Developers
Classifier: Intended Audience :: Science/Research
Classifier: Programming Language :: Python :: 3
Classifier: Programming Language :: Python :: 3.9
Classifier: Programming Language :: Python :: 3.10
Classifier: Programming Language :: Python :: 3.11
Classifier: Programming Language :: Python :: 3.12
Classifier: License :: OSI Approved :: MIT License
Classifier: Topic :: Scientific/Engineering
Classifier: Development Status :: 5 - Production/Stable
License-File: LICENSE
Requires-Dist: nbconvert>=7.16.4
Requires-Dist: requests
Requires-Dist: click==8.1.7
Requires-Dist: attrs>=22.2.0
Requires-Dist: twine>=5.1.1
Requires-Dist: mkdocs-mermaid2-plugin>=1.2.1
Requires-Dist: mkdocs>=1.6.0
Requires-Dist: mkdocs-material>=9.5.30
Requires-Dist: pip_audit==2.7.3
Requires-Dist: uvicorn
Requires-Dist: jupyter>=1.1.1
Requires-Dist: nbformat
Requires-Dist: streamlit>=1.39.0
Requires-Dist: stdlib-list
Requires-Dist: packaging
Requires-Dist: pandas
Requires-Dist: setuptools>=78.1.1
Requires-Dist: fastapi
Requires-Dist: numpy==1.26.0
Requires-Dist: wheel>=0.44.0
Requires-Dist: pyyaml
Dynamic: author
Dynamic: author-email
Dynamic: classifier
Dynamic: description
Dynamic: description-content-type
Dynamic: home-page
Dynamic: keywords
Dynamic: license
Dynamic: license-file
Dynamic: requires-dist
Dynamic: summary
